spatialdyn-1.5.2.dist-info/LICENSE
spatialdyn-1.5.2.dist-info/top_level.txt
spatialdyn-1.5.2.dist-info/WHEEL
spatialdyn-1.5.2.dist-info/METADATA
spatialdyn-1.5.2.dist-info/RECORD
spatialdyn/libtinyxml2.so.8
spatialdyn/spatialdyn.cpython-39-x86_64-linux-gnu.so
spatialdyn/libyaml-cpp.so.0.6
spatialdyn/opspace_control.py
spatialdyn/__init__.py
spatialdyn/joint_space_control.py
spatialdyn/libyaml-cpp.so.0.6.3
spatialdyn/libspatial_dyn.so
spatialdyn/libtinyxml2.so
spatialdyn/libyaml-cpp.so
spatialdyn/libtinyxml2.so.8.0.0
spatialdyn/lib64/cmake/spatial_dyn/spatial_dynTargets-release.cmake
spatialdyn/lib64/cmake/spatial_dyn/spatial_dynConfig.cmake
spatialdyn/lib64/cmake/spatial_dyn/spatial_dynTargets.cmake
spatialdyn/lib64/cmake/spatial_dyn/spatial_dynConfigVersion.cmake
spatialdyn/include/spatial_dyn/spatial_dyn.h
spatialdyn/include/spatial_dyn/eigen/spatial_motion.h
spatialdyn/include/spatial_dyn/eigen/spatial_motion_base.h
spatialdyn/include/spatial_dyn/eigen/spatial_declarations.h
spatialdyn/include/spatial_dyn/eigen/spatial_force_base.h
spatialdyn/include/spatial_dyn/eigen/spatial_math.h
spatialdyn/include/spatial_dyn/eigen/spatial_inertia.h
spatialdyn/include/spatial_dyn/eigen/spatial_force.h
spatialdyn/include/spatial_dyn/algorithms/dynamics_derivatives.h
spatialdyn/include/spatial_dyn/algorithms/opspace_dynamics.h
spatialdyn/include/spatial_dyn/algorithms/forward_kinematics.h
spatialdyn/include/spatial_dyn/algorithms/inverse_dynamics.h
spatialdyn/include/spatial_dyn/algorithms/forward_dynamics.h
spatialdyn/include/spatial_dyn/algorithms/discrete_dynamics.h
spatialdyn/include/spatial_dyn/algorithms/inverse_kinematics.h
spatialdyn/include/spatial_dyn/algorithms/simulation.h
spatialdyn/include/spatial_dyn/structs/graphics.h
spatialdyn/include/spatial_dyn/structs/articulated_body.h
spatialdyn/include/spatial_dyn/structs/options.h
spatialdyn/include/spatial_dyn/structs/articulated_body_cache.h
spatialdyn/include/spatial_dyn/structs/rigid_body.h
spatialdyn/include/spatial_dyn/structs/joint.h
spatialdyn/include/spatial_dyn/parsers/yaml.h
spatialdyn/include/spatial_dyn/parsers/urdf.h
