Metadata-Version: 2.1
Name: spatialdyn
Version: 1.5.2
Summary: Rigid body dynamics library
Author-email: Toki Migimatsu <takatoki@cs.stanford.edu>
License: MIT License
Project-URL: Homepage, https://github.com/tmigimatsu/spatial-dyn.git
Classifier: Programming Language :: Python :: 3
Classifier: License :: OSI Approved :: MIT License
Classifier: Operating System :: OS Independent
Requires-Python: >=3.7
License-File: LICENSE
